{"about_index.md":"D3ve5SNZ","bm_daily.md":"D0WfrWTT","bm_githubstar.md":"DOcaISK8","bm_index.md":"CL4Byec2","bm_onlinetools.md":"DnCrd5yq","bm_others.md":"ClFAzGom","bm_searchtools.md":"CO3sGQ5_","course_index.md":"P4A_lWTp","course_roco_daily.md":"DyxM5izR","course_roco_flash.md":"ChObyTcz","course_roco_fz.md":"CFnUD2ll","course_roco_gn.md":"DMIwcmnT","course_roco_revert.md":"wK5rsQtc","index.md":"C5_Zak0c","weeks_anime_fridays.md":"DrjrUxa3","weeks_anime_monday.md":"BH6CarJJ","weeks_anime_saturdays.md":"CW_-9pwF","weeks_anime_sunday.md":"DLXr1CXM","weeks_anime_thursdays.md":"BB1H5acJ","weeks_anime_tuesday.md":"7VtYWQKD","weeks_anime_wednesdays.md":"D-FxO1x8","weeks_index.md":"CohPQrJA","weeks_manga_fridays.md":"20Uw1F2s","weeks_manga_monday.md":"CoVpAPYW","weeks_manga_saturdays.md":"rvi3oZG_","weeks_manga_sunday.md":"v2EUKV-6","weeks_manga_thursdays.md":"CearQPOz","weeks_manga_tuesday.md":"B3pR-MUr","weeks_manga_wednesdays.md":"DGFpFmqB"}
